django_wechat_api-2.0.0.dist-info/DESCRIPTION.rst
django_wechat_api-2.0.0.dist-info/METADATA
django_wechat_api-2.0.0.dist-info/RECORD
django_wechat_api-2.0.0.dist-info/WHEEL
django_wechat_api-2.0.0.dist-info/metadata.json
django_wechat_api-2.0.0.dist-info/top_level.txt
enterprise_api/__init__.py
enterprise_api/access_token.py
enterprise_api/admin.py
enterprise_api/how_old.py
enterprise_api/models.py
enterprise_api/receive_event.py
enterprise_api/receive_message.py
enterprise_api/response_message.py
enterprise_api/send_message.py
enterprise_api/sender.py
enterprise_api/tests.py
enterprise_api/tuling_robot.py
enterprise_api/urls.py
enterprise_api/views.py
enterprise_api/migrations/__init__.py
enterprise_api/utils/Sample.py
enterprise_api/utils/WXBizMsgCrypt.py
enterprise_api/utils/__init__.py
enterprise_api/utils/ierror.py
wechat_api/__init__.py
wechat_api/admin.py
wechat_api/how_old.py
wechat_api/models.py
wechat_api/receive_event.py
wechat_api/receive_message.py
wechat_api/response_message.py
wechat_api/tests.py
wechat_api/tuling_robot.py
wechat_api/urls.py
wechat_api/views.py
wechat_api/migrations/__init__.py
