Metadata-Version: 2.0
Name: django-wechat-api
Version: 2.0.0
Summary: Pure python/django for wechat official account interface.
Home-page: https://github.com/crazy-canux/django-wechat-api
Author: Canux CHENG
Author-email: canuxcheng@gmail.com
License: GPL
Keywords: python django wechat
Platform: any
Classifier: Development Status :: 5 - Production/Stable
Classifier: Environment :: Web Environment
Classifier: Framework :: Django :: 1.8
Classifier: Intended Audience :: Developers
Classifier: Natural Language :: English
Classifier: License :: OSI Approved :: GNU General Public License (GPL)
Classifier: Operating System :: POSIX
Classifier: Programming Language :: Python
Classifier: Programming Language :: Python :: 2.7
Classifier: Topic :: Software Development :: Libraries :: Python Modules
